{
  "pools": [
    {
      "rolls": 1,
      "entries": [
        {
          "type": "minecraft:item",
          "name": "minecraft:diamond",
          "functions": [
            {
              "function": "minecraft:set_count",
              "count": {
                "min": 0,
                "max": 3
              }
            }
          ]
        }
      ]
    },
    {
      "rolls": 1,
      "entries": [
        {
          "type": "minecraft:item",
          "name": "minecraft:enchanted_golden_apple",
          "functions": [
            {
              "function": "minecraft:set_count",
              "count": {
                "min": 0,
                "max": 1
              }
            }
          ]
        }
      ]
    },
    {
      "rolls": 1,
      "entries": [
        {
          "type": "minecraft:item",
          "name": "minecraft:experience_bottle",
          "functions": [
            {
              "function": "minecraft:set_count",
              "count": {
                "min": 0,
                "max": 2
              }
            }
          ]
        }
      ]
    },
    {
      "rolls": 1,
      "entries": [
        {
          "type": "minecraft:item",
          "name": "minecraft:lapis_lazuli",
          "functions": [
            {
              "function": "minecraft:set_count",
              "count": {
                "min": 0,
                "max": 7
              }
            }
          ]
        }
      ]
    }
  ]
}
